pwd_gen/__init__.py
pwd_gen-0.0.2.dist-info/LICENSE.txt
pwd_gen-0.0.2.dist-info/METADATA
pwd_gen-0.0.2.dist-info/WHEEL
pwd_gen-0.0.2.dist-info/top_level.txt
pwd_gen-0.0.2.dist-info/RECORD
