Metadata-Version: 2.1
Name: pwd-gen
Version: 0.0.2
Summary: simple password generator
Home-page: https://github.com/B00bleaTea/pwd_gen
Author: B00bleTeA
Author-email: asnojus039@gmail.com
License: UNKNOWN
Platform: UNKNOWN
Classifier: Programming Language :: Python :: 3
Classifier: License :: OSI Approved :: MIT License
Classifier: Operating System :: OS Independent
Requires-Python: >=3.8
